sdbus_async/modemmanager/modemmanager/__init__.py
sdbus_async/modemmanager/modemmanager/enums.py
sdbus_async/modemmanager/modemmanager/interfaces_bearer.py
sdbus_async/modemmanager/modemmanager/interfaces_call.py
sdbus_async/modemmanager/modemmanager/interfaces_modem.py
sdbus_async/modemmanager/modemmanager/interfaces_root.py
sdbus_async/modemmanager/modemmanager/interfaces_sim.py
sdbus_async/modemmanager/modemmanager/interfaces_sms.py
sdbus_async/modemmanager/modemmanager/objects.py
sdbus_async/modemmanager/modemmanager/py.typed
sdbus_block/modemmanager/modemmanager/__init__.py
sdbus_block/modemmanager/modemmanager/enums.py
sdbus_block/modemmanager/modemmanager/interfaces_3gpp.py
sdbus_block/modemmanager/modemmanager/interfaces_bearer.py
sdbus_block/modemmanager/modemmanager/interfaces_call.py
sdbus_block/modemmanager/modemmanager/interfaces_location.py
sdbus_block/modemmanager/modemmanager/interfaces_modem.py
sdbus_block/modemmanager/modemmanager/interfaces_root.py
sdbus_block/modemmanager/modemmanager/interfaces_sim.py
sdbus_block/modemmanager/modemmanager/interfaces_simple.py
sdbus_block/modemmanager/modemmanager/interfaces_sms.py
sdbus_block/modemmanager/modemmanager/interfaces_time.py
sdbus_block/modemmanager/modemmanager/objects.py
sdbus_block/modemmanager/modemmanager/py.typed
sdbus_modemmanager-1.0.3.dist-info/METADATA
sdbus_modemmanager-1.0.3.dist-info/WHEEL
sdbus_modemmanager-1.0.3.dist-info/licenses/COPYING.LESSER
sdbus_modemmanager-1.0.3.dist-info/RECORD
