Metadata-Version: 2.4
Name: sdbus-modemmanager
Version: 1.0.3
Summary: ModemManager binds for sdbus.
License: LGPL-2.1-or-later
License-File: COPYING.LESSER
Keywords: sdbus,modemmanager,dbus
Author: longqi
Author-email: longqi90@gmail.com
Requires-Python: >=3.7,<4.0
Classifier: Development Status :: 5 - Production/Stable
Classifier: Intended Audience :: Developers
Classifier: License :: OSI Approved :: GNU Lesser General Public License v2 or later (LGPLv2+)
Classifier: Operating System :: POSIX :: Linux
Classifier: Programming Language :: Python :: 3 :: Only
Classifier: Topic :: Software Development :: Libraries :: Python Modules
Requires-Dist: sdbus (>=0.8rc2)
